homeassistant_cli/__init__.py
homeassistant_cli/autocompletion.py
homeassistant_cli/cli.py
homeassistant_cli/config.py
homeassistant_cli/const.py
homeassistant_cli/exceptions.py
homeassistant_cli/hassconst.py
homeassistant_cli/helper.py
homeassistant_cli/package_constraints.txt
homeassistant_cli/remote.py
homeassistant_cli/yaml.py
homeassistant_cli/plugins/area.py
homeassistant_cli/plugins/completion.py
homeassistant_cli/plugins/config.py
homeassistant_cli/plugins/device.py
homeassistant_cli/plugins/discover.py
homeassistant_cli/plugins/entity.py
homeassistant_cli/plugins/event.py
homeassistant_cli/plugins/ha.py
homeassistant_cli/plugins/info.py
homeassistant_cli/plugins/map.py
homeassistant_cli/plugins/raw.py
homeassistant_cli/plugins/service.py
homeassistant_cli/plugins/state.py
homeassistant_cli/plugins/system.py
homeassistant_cli/plugins/template.py
homeassistant_cli-0.9.4.dist-info/LICENSE.md
homeassistant_cli-0.9.4.dist-info/METADATA
homeassistant_cli-0.9.4.dist-info/WHEEL
homeassistant_cli-0.9.4.dist-info/entry_points.txt
homeassistant_cli-0.9.4.dist-info/top_level.txt
homeassistant_cli-0.9.4.dist-info/RECORD
