Metadata-Version: 2.1
Name: homeassistant-cli
Version: 0.9.4
Summary: Command-line tool for Home Assistant.
Home-page: https://github.com/home-assistant-ecosystem/home-assistant-cli
Author: The Home Assistant CLI Authors
Author-email: fabian@affolter-engineering.ch
License: Apache License 2.0
Download-URL: https://github.com/home-assistant-ecosystem/home-assistant-cli/archive/0.9.4.zip
Project-URL: Bug Reports, https://github.com/home-assistant-ecosystem/home-assistant-cli/issues
Project-URL: Dev Docs, https://developers.home-assistant.io/
Project-URL: Discord, https://discordapp.com/invite/c5DvZ4e
Project-URL: Forum, https://community.home-assistant.io/
Keywords: home,automation
Platform: any
Classifier: Development Status :: 3 - Alpha
Classifier: Intended Audience :: End Users/Desktop
Classifier: Intended Audience :: Developers
Classifier: License :: OSI Approved :: Apache Software License
Classifier: Operating System :: OS Independent
Classifier: Programming Language :: Python :: 3.8
Classifier: Programming Language :: Python :: 3.9
Classifier: Topic :: Home Automation
Requires-Python: >=3.8.0
Requires-Dist: aiohttp (<4,>=3.7.4)
Requires-Dist: click-log (<0.4,>=0.3.2)
Requires-Dist: click (<9,>=8)
Requires-Dist: dateparser (<0.8,>=0.7.1)
Requires-Dist: jinja2 (>=2.10)
Requires-Dist: jsonpath-ng (<2,>=1.5.1)
Requires-Dist: netdisco (<3,>=2.8.3)
Requires-Dist: regex (>=2021.4.4)
Requires-Dist: ruamel.yaml (<0.18,>=0.16.5)
Requires-Dist: requests (<3,>=2.22.0)
Requires-Dist: tabulate (<0.9,>=0.8.3)
Provides-Extra: test
Requires-Dist: black (<21,>=20.8b1) ; extra == 'test'
Requires-Dist: codecov (<3,>=2.0.15) ; extra == 'test'
Requires-Dist: coveralls (<2,>=1.2.0) ; extra == 'test'
Requires-Dist: flake8 (<4,>=3.9) ; extra == 'test'
Requires-Dist: flake8-docstrings (<2,>=1.3.0) ; extra == 'test'
Requires-Dist: mock-open (<1.5,>=1.4) ; extra == 'test'
Requires-Dist: mypy (<0.900,>=0.800) ; extra == 'test'
Requires-Dist: pydocstyle (<7,>=6) ; extra == 'test'
Requires-Dist: pylint (<3,>=2.7) ; extra == 'test'
Requires-Dist: pytest (<7,>=6) ; extra == 'test'
Requires-Dist: pytest-cov (<3,>=2.11) ; extra == 'test'
Requires-Dist: pytest-sugar (<0.10,>=0.9.4) ; extra == 'test'
Requires-Dist: pytest-timeout (<2,>=1.4) ; extra == 'test'
Requires-Dist: requests-mock (<2,>=1.8.0) ; extra == 'test'
Requires-Dist: twine (<2,>=1.13.0) ; extra == 'test'
Requires-Dist: wheel (<0.40,>=0.33.1) ; extra == 'test'
